biskit_components/__init__.py
biskit_components/__version__.py
biskit_components/_version.py
biskit_components/_components/AlertIcon.py
biskit_components/_components/ArrowIcon.py
biskit_components/_components/BellIcon.py
biskit_components/_components/BigBanner.py
biskit_components/_components/BigNumberInfoContents.py
biskit_components/_components/BiskitIcon.py
biskit_components/_components/Board.py
biskit_components/_components/BoardItem.py
biskit_components/_components/Breadcrumbs.py
biskit_components/_components/BulletIcon.py
biskit_components/_components/Button.py
biskit_components/_components/CalendarIcon.py
biskit_components/_components/CancelIcon.py
biskit_components/_components/ChartInfoContents.py
biskit_components/_components/ChartWrapper.py
biskit_components/_components/CheckIcon.py
biskit_components/_components/Checkbox.py
biskit_components/_components/CloseIcon.py
biskit_components/_components/CountrySelect.py
biskit_components/_components/DailyHistories.py
biskit_components/_components/DashboardHeader.py
biskit_components/_components/DashboardInformation.py
biskit_components/_components/DashboardNotice.py
biskit_components/_components/DashboardTab.py
biskit_components/_components/DateInput.py
biskit_components/_components/DatePicker.py
biskit_components/_components/DetailButton.py
biskit_components/_components/DownloadButton.py
biskit_components/_components/DownloadIcon.py
biskit_components/_components/DropDownArrowIcon.py
biskit_components/_components/FilterResetButton.py
biskit_components/_components/FoldIcon.py
biskit_components/_components/Footer.py
biskit_components/_components/Fragment.py
biskit_components/_components/Header.py
biskit_components/_components/HelpIcon.py
biskit_components/_components/HistoryContents.py
biskit_components/_components/Home.py
biskit_components/_components/HomeIcon.py
biskit_components/_components/I18nContextProvider.py
biskit_components/_components/InfoButton.py
biskit_components/_components/InfoIcon.py
biskit_components-0.0.3.dist-info/METADATA
biskit_components-0.0.3.dist-info/WHEEL
biskit_components-0.0.3.dist-info/top_level.txt
biskit_components-0.0.3.dist-info/RECORD
