Metadata-Version: 2.1
Name: biskit-components
Version: 0.0.3
Author: devsisters
Author-email: web@devsisters.com
Classifier: Framework :: Dash
Classifier: Programming Language :: Python :: 3.10
Classifier: Programming Language :: Python :: 3.11
Requires-Python: >=3.10, <4
Requires-Dist: dash (>=2.7.0)
Provides-Extra: pandas
Requires-Dist: numpy ; extra == 'pandas'
Requires-Dist: pandas ; extra == 'pandas'
